{"title":"The Harms of Historical Hyperbole.","markdown":{"yaml":{"title":"The Harms of Historical Hyperbole.","author":"**Dylan Spicker**","image":"/img/icons/talk.svg","categories":["talk"],"description":"Talk given at the [Statistics and Actuarial Sciences Student Seminar Series (SASSSS)](https://web.archive.org/web/20210629212849/https://uwaterloo.ca/statistics-and-actuarial-science/events/department-seminar-dylan-spicker). (2021, Waterloo). ([PDF of Slides](/pdf/Dylan%20Spicker%20-%20SASSSS%20-%202021.pdf). Note, these slides were originally presented as an interactive presentation, rather than PDF, so some is lost in translation. I am working on figuring out how to display the presentation here better! Apologies.)","date":"2021-06-29"},"containsRefs":false,"markdown":"\n"},"formats":{"html":{"execute":{"fig-width":7,"fig-height":5,"fig-format":"retina","fig-dpi":96,"df-print":"default","error":false,"eval":true,"cache":null,"freeze":false,"echo":true,"output":true,"warning":true,"include":true,"keep-md":false,"keep-ipynb":false,"ipynb":null,"enabled":null,"daemon":null,"daemon-restart":false,"debug":false,"ipynb-filters":[],"engine":"markdown"},"render":{"keep-tex":false,"keep-yaml":false,"keep-source":false,"keep-hidden":false,"prefer-html":false,"output-divs":true,"output-ext":"html","fig-align":"default","fig-pos":null,"fig-env":null,"code-fold":"none","code-overflow":"scroll","code-link":false,"code-line-numbers":false,"code-tools":false,"tbl-colwidths":"auto","merge-includes":true,"latex-auto-mk":true,"latex-auto-install":true,"latex-clean":true,"latex-max-runs":10,"latex-makeindex":"makeindex","latex-makeindex-opts":[],"latex-tlmgr-opts":[],"latex-input-paths":[],"latex-output-dir":null,"link-external-icon":false,"link-external-newwindow":false,"self-contained-math":false,"format-resources":[]},"pandoc":{"standalone":true,"wrap":"none","default-image-extension":"png","to":"html","css":["../styles.css"],"toc":false,"output-file":"historical_hyperbole.html"},"language":{},"metadata":{"lang":"en","fig-responsive":true,"quarto-version":"1.1.168","theme":"simplex","page-layout":"full","title":"The Harms of Historical Hyperbole.","author":"**Dylan Spicker**","image":"/img/icons/talk.svg","categories":["talk"],"description":"Talk given at the [Statistics and Actuarial Sciences Student Seminar Series (SASSSS)](https://web.archive.org/web/20210629212849/https://uwaterloo.ca/statistics-and-actuarial-science/events/department-seminar-dylan-spicker). (2021, Waterloo). ([PDF of Slides](/pdf/Dylan%20Spicker%20-%20SASSSS%20-%202021.pdf). Note, these slides were originally presented as an interactive presentation, rather than PDF, so some is lost in translation. I am working on figuring out how to display the presentation here better! Apologies.)","date":"2021-06-29"},"extensions":{"book":{"multiFile":true}}}}}